girard/__init__.py
girard/generate_cone.py
girard/linear_algebra.py
girard/memoize.py
girard/monte_carlo.py
girard/plotting.py
girard/sampling.py
girard/series.py
girard/series_convergence.py
girard/utils.py
girard/resources/VERSION
solidus/__init__.py
solidus/generate_cone.py
solidus/linear_algebra.py
solidus/memoize.py
solidus/monte_carlo.py
solidus/plotting.py
solidus/sampling.py
solidus/series.py
solidus/series_convergence.py
solidus/utils.py
solidus/resources/VERSION
girard-0.1.0.dist-info/METADATA
girard-0.1.0.dist-info/WHEEL
girard-0.1.0.dist-info/top_level.txt
girard-0.1.0.dist-info/RECORD
