Metadata-Version: 2.1
Name: girard
Version: 0.1.0
Summary: Python package for approximating solid angles in high dimensions
Home-page: https://github.com/gnsantos/girard
Author: Gervásio Protásio dos Santos Neto
License: UNKNOWN
Platform: UNKNOWN
Classifier: Programming Language :: Python :: 3.6
Requires-Dist: seaborn
Requires-Dist: scipy
Requires-Dist: matplotlib
Requires-Dist: numpy
Requires-Dist: toolz
Provides-Extra: test_deps
Requires-Dist: pytest (<6,>=4.3.1) ; extra == 'test_deps'
Requires-Dist: pytest-xdist (<2,>=1.26.1) ; extra == 'test_deps'
